realestate_data
