Metadata-Version: 2.1
Name: realestate-data
Version: 0.1.0
Summary: Realestate Data
Home-page: https://github.com/storerjeremy/realestate-data
Author: Jeremy Storer
Author-email: storerjeremy@gmail.com
License: UNKNOWN
Platform: UNKNOWN
Classifier: Programming Language :: Python :: 3
Classifier: License :: OSI Approved :: MIT License
Classifier: Operating System :: OS Independent
